intelmq/__init__.py
intelmq/version.py
intelmq/bin/__init__.py
intelmq/bin/intelmq_generate_misp_objects_templates.py
intelmq/bin/intelmq_psql_initdb.py
intelmq/bin/intelmqctl.py
intelmq/bin/intelmqdump.py
intelmq/bin/intelmqsetup.py
intelmq/bin/rewrite_config_files.py
intelmq/bots/__init__.py
intelmq/bots/collectors/alienvault_otx/REQUIREMENTS.txt
intelmq/bots/collectors/alienvault_otx/__init__.py
intelmq/bots/collectors/alienvault_otx/collector.py
intelmq/bots/collectors/amqp/REQUIREMENTS.txt
intelmq/bots/collectors/amqp/__init__.py
intelmq/bots/collectors/amqp/collector_amqp.py
intelmq/bots/collectors/api/REQUIREMENTS.txt
intelmq/bots/collectors/api/__init__.py
intelmq/bots/collectors/api/collector_api.py
intelmq/bots/collectors/blueliv/REQUIREMENTS.txt
intelmq/bots/collectors/blueliv/__init__.py
intelmq/bots/collectors/blueliv/collector_crimeserver.py
intelmq/bots/collectors/calidog/REQUIREMENTS.txt
intelmq/bots/collectors/calidog/__init__.py
intelmq/bots/collectors/calidog/collector_certstream.py
intelmq/bots/collectors/eset/REQUIREMENTS.txt
intelmq/bots/collectors/eset/__init__.py
intelmq/bots/collectors/eset/collector.py
intelmq/bots/collectors/file/__init__.py
intelmq/bots/collectors/file/collector_file.py
intelmq/bots/collectors/fireeye/REQUIREMENTS.txt
intelmq/bots/collectors/fireeye/__init__.py
intelmq/bots/collectors/fireeye/collector_mas.py
intelmq/bots/collectors/github_api/__init__.py
intelmq/bots/collectors/github_api/_collector_github_api.py
intelmq/bots/collectors/github_api/collector_github_contents_api.py
intelmq/bots/collectors/http/REQUIREMENTS.txt
intelmq/bots/collectors/http/__init__.py
intelmq/bots/collectors/http/collector_http.py
intelmq/bots/collectors/http/collector_http_stream.py
intelmq/bots/collectors/kafka/REQUIREMENTS.txt
intelmq/bots/collectors/kafka/collector.py
intelmq/bots/collectors/mail/REQUIREMENTS.txt
intelmq/bots/collectors/mail/__init__.py
intelmq/bots/collectors/mail/_lib.py
intelmq-3.4.0.dist-info/AGPL-3.0-only.txt
intelmq-3.4.0.dist-info/AGPL-3.0-or-later.txt
intelmq-3.4.0.dist-info/CC0-1.0.txt
intelmq-3.4.0.dist-info/LICENSE
intelmq-3.4.0.dist-info/METADATA
intelmq-3.4.0.dist-info/WHEEL
intelmq-3.4.0.dist-info/entry_points.txt
intelmq-3.4.0.dist-info/top_level.txt
intelmq-3.4.0.dist-info/RECORD
