Metadata-Version: 2.2
Name: intelmq
Version: 3.4.0
Summary: IntelMQ is a solution for IT security teams for collecting and processing security feeds using a message queuing protocol.
Home-page: https://github.com/certtools/intelmq/
Author: IntelMQ Community
Maintainer: Sebastian Wagner
Maintainer-email: intelmq-dev@lists.cert.at
License: AGPLv3
Project-URL: Documentation, https://docs.intelmq.org/
Project-URL: Source and Issue Tracker, https://github.com/certtools/intelmq/
Keywords: incident handling cert csirt
Classifier: Development Status :: 5 - Production/Stable
Classifier: Environment :: Console
Classifier: Intended Audience :: Information Technology
Classifier: Intended Audience :: System Administrators
Classifier: Intended Audience :: Telecommunications Industry
Classifier: License :: OSI Approved :: GNU Affero General Public License v3
Classifier: Operating System :: POSIX :: Linux
Classifier: Programming Language :: Python
Classifier: Programming Language :: Python :: 3
Classifier: Programming Language :: Python :: 3.9
Classifier: Programming Language :: Python :: 3.10
Classifier: Programming Language :: Python :: 3.11
Classifier: Programming Language :: Python :: 3.12
Classifier: Programming Language :: Python :: 3.13
Classifier: Programming Language :: Python :: 3 :: Only
Classifier: Programming Language :: Python :: Implementation :: CPython
Classifier: Topic :: Security
Requires-Python: >=3.8
License-File: LICENSE
License-File: LICENSES/AGPL-3.0-only.txt
License-File: LICENSES/AGPL-3.0-or-later.txt
License-File: LICENSES/CC0-1.0.txt
Requires-Dist: dnspython>=2.0.0
Requires-Dist: psutil>=1.2.1
Requires-Dist: python-dateutil>=2.5
Requires-Dist: python-termstyle>=0.1.10
Requires-Dist: redis>=2.10
Requires-Dist: requests>=2.2.0
Requires-Dist: ruamel.yaml
Provides-Extra: development
Requires-Dist: Cerberus!=1.3.0; extra == "development"
Requires-Dist: requests_mock; extra == "development"
Requires-Dist: mkdocs-material; extra == "development"
Requires-Dist: mike; extra == "development"
Requires-Dist: lunr; extra == "development"
Requires-Dist: pygments; extra == "development"
Requires-Dist: mkdocstrings[python]; extra == "development"
Requires-Dist: mkdocs-material; extra == "development"
Requires-Dist: mkdocs-glightbox; extra == "development"
Requires-Dist: mkdocs-redirects; extra == "development"
Requires-Dist: mkdocs-minify-plugin; extra == "development"
Dynamic: classifier
Dynamic: description
Dynamic: description-content-type
Dynamic: home-page
Dynamic: keywords
Dynamic: license
Dynamic: maintainer
Dynamic: maintainer-email
Dynamic: project-url
Dynamic: provides-extra
Dynamic: requires-dist
Dynamic: requires-python
Dynamic: summary
